aegis/__init__.py
aegis/__main__.py
aegis/constants.py
aegis/cli/__init__.py
aegis/cli/callbacks.py
aegis/cli/interactive.py
aegis/cli/utils.py
aegis/cli/validation.py
aegis/cli/validators.py
aegis/commands/__init__.py
aegis/commands/add.py
aegis/commands/add_service.py
aegis/commands/components.py
aegis/commands/init.py
aegis/commands/remove.py
aegis/commands/remove_service.py
aegis/commands/services.py
aegis/commands/update.py
aegis/commands/version.py
aegis/config/__init__.py
aegis/config/defaults.py
aegis/config/shared_files.py
aegis/core/__init__.py
aegis/core/ai_service_parser.py
aegis/core/component_files.py
aegis/core/component_utils.py
aegis/core/components.py
aegis/core/copier_manager.py
aegis/core/copier_updater.py
aegis/core/dependency_resolver.py
aegis/core/manual_updater.py
aegis/core/migration_generator.py
aegis/core/post_gen_tasks.py
aegis/core/project_map.py
aegis/core/service_resolver.py
aegis/core/services.py
aegis/core/template_cleanup.py
aegis/core/template_generator.py
aegis/core/verbosity.py
aegis/core/version_compatibility.py
aegis/templates/copier-aegis-project/{{ project_slug }}/.copier-answers.yml.jinja
aegis/templates/copier-aegis-project/{{ project_slug }}/.dockerignore
aegis/templates/copier-aegis-project/{{ project_slug }}/.env.example.jinja
aegis/templates/copier-aegis-project/{{ project_slug }}/.gitignore
aegis/templates/copier-aegis-project/{{ project_slug }}/.python-version.jinja
aegis/templates/copier-aegis-project/{{ project_slug }}/Dockerfile.jinja
aegis/templates/copier-aegis-project/{{ project_slug }}/Makefile.jinja
aegis/templates/copier-aegis-project/{{ project_slug }}/README.md.jinja
aegis/templates/copier-aegis-project/{{ project_slug }}/docker-compose.yml.jinja
aegis/templates/copier-aegis-project/{{ project_slug }}/mkdocs.yml.jinja
aegis/templates/copier-aegis-project/{{ project_slug }}/pyproject.toml.jinja
aegis/templates/copier-aegis-project/{{ project_slug }}/alembic/alembic.ini.jinja
aegis_stack-0.5.4.dist-info/METADATA
aegis_stack-0.5.4.dist-info/WHEEL
aegis_stack-0.5.4.dist-info/entry_points.txt
aegis_stack-0.5.4.dist-info/licenses/LICENSE
aegis_stack-0.5.4.dist-info/RECORD
