Metadata-Version: 2.4
Name: aegis-stack
Version: 0.5.4
Summary: A production-ready Python foundation for builders who refuse to wait. Try: uvx aegis-stack init my-project
Project-URL: Homepage, https://lbedner.github.io/aegis-stack/
Project-URL: Documentation, https://lbedner.github.io/aegis-stack/
Project-URL: Repository, https://github.com/lbedner/aegis-stack.git
Project-URL: Issues, https://github.com/lbedner/aegis-stack/issues
Author-email: Leonard Bedner <gamecoder99@gmail.com>
License: MIT
License-File: LICENSE
Keywords: boilerplate,cli,cookiecutter,database,fastapi,generator,python,scaffold,scheduler,stack,template,uvx,worker
Classifier: Development Status :: 4 - Beta
Classifier: Environment :: Console
Classifier: Intended Audience :: Developers
Classifier: License :: OSI Approved :: MIT License
Classifier: Natural Language :: English
Classifier: Operating System :: OS Independent
Classifier: Programming Language :: Python :: 3
Classifier: Programming Language :: Python :: 3.11
Classifier: Programming Language :: Python :: 3.12
Classifier: Programming Language :: Python :: 3.13
Classifier: Programming Language :: Python :: 3.14
Classifier: Topic :: Internet :: WWW/HTTP :: HTTP Servers
Classifier: Topic :: Software Development :: Code Generators
Classifier: Topic :: Software Development :: Libraries :: Application Frameworks
Classifier: Typing :: Typed
Requires-Python: <3.15,>=3.11
Requires-Dist: copier>=9.11.2
Requires-Dist: filelock>=3.20.1
Requires-Dist: packaging>=24.0
Requires-Dist: pillow>=11.3.0
Requires-Dist: rich>=13.0.0
Requires-Dist: typer>=0.9.0
Requires-Dist: urllib3>=2.6.3
Provides-Extra: dev
Requires-Dist: pip-audit>=2.6.0; extra == 'dev'
Requires-Dist: pre-commit>=3.7.0; extra == 'dev'
Requires-Dist: pytest-asyncio>=0.23.0; extra == 'dev'
Requires-Dist: pytest>=8.0.0; extra == 'dev'
Requires-Dist: ruff>=0.1.0; extra == 'dev'
Requires-Dist: ty>=0.0.8; extra == 'dev'
Provides-Extra: docs
Requires-Dist: mkdocs-gen-files>=0.5.0; extra == 'docs'
Requires-Dist: mkdocs-glightbox>=0.3.0; extra == 'docs'
Requires-Dist: mkdocs-material>=9.5.0; extra == 'docs'
Requires-Dist: mkdocs-mermaid2-plugin>=1.1.0; extra == 'docs'
Requires-Dist: mkdocs>=1.5.0; extra == 'docs'
Requires-Dist: mkdocstrings[python]>=0.24.0; extra == 'docs'
Requires-Dist: pymdown-extensions>=10.0.0; extra == 'docs'
